{"uuid":"fd070b1a-3024-4d95-bcaa-8d6ec775d950","passwd":"bc0caeef-8dce-4494-909a-17b15f9f04da","version":1,"svc_table":{"services":[{"id":7902,"svc_type":5,"mac":"50:e6:36:28:74:6b","address":"192.168.178.1:80","path":"","static_svc":false,"last_seen":1764744473,"active":true},{"id":44714,"svc_type":5,"mac":"0a:b4:fe:16:76:3d","address":"192.168.178.42:80","path":"","static_svc":false,"last_seen":1764744473,"active":true},{"id":48342,"svc_type":5,"mac":"0a:b4:fe:20:9f:65","address":"192.168.178.35:80","path":"","static_svc":false,"last_seen":1764744473,"active":true},{"id":42513,"svc_type":5,"mac":"56:e6:36:da:35:49","address":"192.168.178.29:80","path":"","static_svc":false,"last_seen":1764744473,"active":true}]}}